xournal_converters/__init__.py
xournal_converters/html.py
xournal_converters/pdf.py
xournal_converters-0.0.9.dist-info/DESCRIPTION.rst
xournal_converters-0.0.9.dist-info/METADATA
xournal_converters-0.0.9.dist-info/RECORD
xournal_converters-0.0.9.dist-info/WHEEL
xournal_converters-0.0.9.dist-info/entry_points.txt
xournal_converters-0.0.9.dist-info/metadata.json
xournal_converters-0.0.9.dist-info/top_level.txt
