Metadata-Version: 2.0
Name: xournal-converters
Version: 0.0.9
Summary: Python scripts for converting Xournal documents to HTML and PDF.
Home-page: https://github.com/catch22/xournal-converters
Author: Michael Walter
Author-email: michael.walter@gmail.com
License: MIT
Platform: UNKNOWN
Classifier: Development Status :: 3 - Alpha
Classifier: Programming Language :: Python :: 2
Classifier: Programming Language :: Python :: 2.7
Classifier: Programming Language :: Python :: 3
Classifier: Programming Language :: Python :: 3.5
Classifier: Environment :: Console
Classifier: License :: OSI Approved :: MIT License
Provides-Extra: dev
Requires-Dist: click
Requires-Dist: reportlab
Requires-Dist: PyPDF2
Provides-Extra: dev
Requires-Dist: pypandoc; extra == 'dev'
Requires-Dist: wheel; extra == 'dev'
Requires-Dist: yapf; extra == 'dev'
Requires-Dist: flake8; extra == 'dev'
Requires-Dist: twine; extra == 'dev'
